odoo8_addon_mail_read_new_window-8.0.1.0.0.99.dev9-py2.7-nspkg.pth
odoo8_addon_mail_read_new_window-8.0.1.0.0.99.dev9.dist-info/DESCRIPTION.rst
odoo8_addon_mail_read_new_window-8.0.1.0.0.99.dev9.dist-info/METADATA
odoo8_addon_mail_read_new_window-8.0.1.0.0.99.dev9.dist-info/RECORD
odoo8_addon_mail_read_new_window-8.0.1.0.0.99.dev9.dist-info/WHEEL
odoo8_addon_mail_read_new_window-8.0.1.0.0.99.dev9.dist-info/metadata.json
odoo8_addon_mail_read_new_window-8.0.1.0.0.99.dev9.dist-info/namespace_packages.txt
odoo8_addon_mail_read_new_window-8.0.1.0.0.99.dev9.dist-info/top_level.txt
odoo_addons/mail_read_new_window/README.rst
odoo_addons/mail_read_new_window/__init__.py
odoo_addons/mail_read_new_window/__openerp__.py
odoo_addons/mail_read_new_window/mail_read_new_window_view.xml
odoo_addons/mail_read_new_window/i18n/de.po
odoo_addons/mail_read_new_window/i18n/es.po
odoo_addons/mail_read_new_window/i18n/fr.po
odoo_addons/mail_read_new_window/i18n/mail_read_new_window.pot
odoo_addons/mail_read_new_window/i18n/sl.po
odoo_addons/mail_read_new_window/static/description/icon.png
odoo_addons/mail_read_new_window/static/src/css/mail_read_new_window.css
odoo_addons/mail_read_new_window/static/src/js/mail_read_new_window.js
odoo_addons/mail_read_new_window/static/src/xml/mail_read_new_window.xml
